{
  "updated": "2026-04-20T11:09:13Z",
  "penalty_rank": 100,
  "predictions": {
    "adriano": [
      {
        "player": "Sinner",
        "predicted_rank": 1
      },
      {
        "player": "Alcaraz",
        "predicted_rank": 2
      },
      {
        "player": "Zverev",
        "predicted_rank": 3
      },
      {
        "player": "De Minaur",
        "predicted_rank": 4
      },
      {
        "player": "Djokovic",
        "predicted_rank": 5
      },
      {
        "player": "Draper",
        "predicted_rank": 6
      },
      {
        "player": "Fritz",
        "predicted_rank": 7
      },
      {
        "player": "Shelton",
        "predicted_rank": 8
      },
      {
        "player": "Musetti",
        "predicted_rank": 9
      },
      {
        "player": "Medvedev",
        "predicted_rank": 10
      }
    ],
    "alessandro": [
      {
        "player": "Sinner",
        "predicted_rank": 1
      },
      {
        "player": "Alcaraz",
        "predicted_rank": 2
      },
      {
        "player": "Zverev",
        "predicted_rank": 3
      },
      {
        "player": "Fritz",
        "predicted_rank": 4
      },
      {
        "player": "De Minaur",
        "predicted_rank": 5
      },
      {
        "player": "Musetti",
        "predicted_rank": 6
      },
      {
        "player": "Fonseca",
        "predicted_rank": 7
      },
      {
        "player": "Shelton",
        "predicted_rank": 8
      },
      {
        "player": "Auger-Aliassime",
        "predicted_rank": 9
      },
      {
        "player": "Rublev",
        "predicted_rank": 10
      }
    ],
    "federico": [
      {
        "player": "Sinner",
        "predicted_rank": 1
      },
      {
        "player": "Alcaraz",
        "predicted_rank": 2
      },
      {
        "player": "Fritz",
        "predicted_rank": 3
      },
      {
        "player": "Shelton",
        "predicted_rank": 4
      },
      {
        "player": "Draper",
        "predicted_rank": 5
      },
      {
        "player": "Zverev",
        "predicted_rank": 6
      },
      {
        "player": "Djokovic",
        "predicted_rank": 7
      },
      {
        "player": "De Minaur",
        "predicted_rank": 8
      },
      {
        "player": "Musetti",
        "predicted_rank": 9
      },
      {
        "player": "Fonseca",
        "predicted_rank": 10
      }
    ],
    "viola": [
      {
        "player": "Sinner",
        "predicted_rank": 1
      },
      {
        "player": "Alcaraz",
        "predicted_rank": 2
      },
      {
        "player": "Djokovic",
        "predicted_rank": 3
      },
      {
        "player": "De Minaur",
        "predicted_rank": 4
      },
      {
        "player": "Zverev",
        "predicted_rank": 5
      },
      {
        "player": "Musetti",
        "predicted_rank": 6
      },
      {
        "player": "Auger-Aliassime",
        "predicted_rank": 7
      },
      {
        "player": "Shelton",
        "predicted_rank": 8
      },
      {
        "player": "Fritz",
        "predicted_rank": 9
      },
      {
        "player": "Medvedev",
        "predicted_rank": 10
      }
    ]
  },
  "players": {
    "zverev": "Zverev",
    "shelton": "Shelton",
    "fonseca": "Fonseca",
    "fritz": "Fritz",
    "medvedev": "Medvedev",
    "draper": "Draper",
    "sinner": "Sinner",
    "de-minaur": "De Minaur",
    "auger-aliassime": "Auger-Aliassime",
    "rublev": "Rublev",
    "musetti": "Musetti",
    "alcaraz": "Alcaraz",
    "djokovic": "Djokovic"
  },
  "weeks": [
    {
      "date": "2026-01-05",
      "distances": {
        "adriano": 6.3246,
        "alessandro": 23.7697,
        "federico": 21.587,
        "viola": 5.0
      },
      "actuals": {
        "zverev": 3,
        "shelton": 8,
        "fonseca": 29,
        "fritz": 9,
        "medvedev": 13,
        "draper": 10,
        "sinner": 2,
        "de-minaur": 6,
        "auger-aliassime": 5,
        "rublev": 16,
        "musetti": 7,
        "alcaraz": 1,
        "djokovic": 4
      }
    },
    {
      "date": "2026-01-12",
      "distances": {
        "adriano": 7.4833,
        "alessandro": 24.0416,
        "federico": 22.9783,
        "viola": 4.0
      },
      "actuals": {
        "zverev": 3,
        "shelton": 8,
        "fonseca": 30,
        "fritz": 9,
        "medvedev": 12,
        "draper": 11,
        "sinner": 2,
        "de-minaur": 6,
        "auger-aliassime": 7,
        "rublev": 14,
        "musetti": 5,
        "alcaraz": 1,
        "djokovic": 4
      }
    },
    {
      "date": "2026-01-19",
      "distances": {
        "adriano": 7.5498,
        "alessandro": 26.096,
        "federico": 24.5967,
        "viola": 4.2426
      },
      "actuals": {
        "zverev": 3,
        "shelton": 7,
        "fonseca": 32,
        "fritz": 9,
        "medvedev": 12,
        "draper": 11,
        "sinner": 2,
        "de-minaur": 6,
        "auger-aliassime": 8,
        "rublev": 15,
        "musetti": 5,
        "alcaraz": 1,
        "djokovic": 4
      }
    },
    {
      "date": "2026-02-02",
      "distances": {
        "adriano": 8.8318,
        "alessandro": 27.5862,
        "federico": 26.8887,
        "viola": 3.873
      },
      "actuals": {
        "zverev": 4,
        "shelton": 9,
        "fonseca": 34,
        "fritz": 7,
        "medvedev": 11,
        "draper": 13,
        "sinner": 2,
        "de-minaur": 6,
        "auger-aliassime": 8,
        "rublev": 14,
        "musetti": 5,
        "alcaraz": 1,
        "djokovic": 3
      }
    },
    {
      "date": "2026-02-09",
      "distances": {
        "adriano": 8.775,
        "alessandro": 27.074,
        "federico": 25.632,
        "viola": 5.1962
      },
      "actuals": {
        "zverev": 4,
        "shelton": 9,
        "fonseca": 33,
        "fritz": 7,
        "medvedev": 11,
        "draper": 12,
        "sinner": 2,
        "de-minaur": 8,
        "auger-aliassime": 6,
        "rublev": 15,
        "musetti": 5,
        "alcaraz": 1,
        "djokovic": 3
      }
    },
    {
      "date": "2026-02-16",
      "distances": {
        "adriano": 8.124,
        "alessandro": 31.6702,
        "federico": 30.4138,
        "viola": 3.3166
      },
      "actuals": {
        "de-minaur": 6,
        "zverev": 4,
        "rublev": 14,
        "shelton": 9,
        "sinner": 2,
        "fonseca": 38,
        "musetti": 5,
        "alcaraz": 1,
        "draper": 12,
        "medvedev": 11,
        "fritz": 8,
        "djokovic": 3,
        "auger-aliassime": 7
      }
    },
    {
      "date": "2026-02-23",
      "distances": {
        "adriano": 10.4881,
        "alessandro": 32.2645,
        "federico": 31.0966,
        "viola": 3.873
      },
      "actuals": {
        "zverev": 4,
        "shelton": 9,
        "fonseca": 38,
        "fritz": 7,
        "medvedev": 11,
        "draper": 15,
        "sinner": 2,
        "de-minaur": 6,
        "auger-aliassime": 8,
        "rublev": 18,
        "musetti": 5,
        "alcaraz": 1,
        "djokovic": 3
      }
    },
    {
      "date": "2026-03-02",
      "distances": {
        "adriano": 9.5917,
        "alessandro": 29.1033,
        "federico": 27.9285,
        "viola": 4.1231
      },
      "actuals": {
        "zverev": 4,
        "shelton": 8,
        "fonseca": 35,
        "fritz": 7,
        "medvedev": 11,
        "draper": 14,
        "sinner": 2,
        "de-minaur": 6,
        "auger-aliassime": 9,
        "rublev": 17,
        "musetti": 5,
        "alcaraz": 1,
        "djokovic": 3
      }
    },
    {
      "date": "2026-03-09",
      "distances": {
        "adriano": 9.5917,
        "alessandro": 29.1033,
        "federico": 27.9285,
        "viola": 4.1231
      },
      "actuals": {
        "draper": 14,
        "zverev": 4,
        "medvedev": 11,
        "auger-aliassime": 9,
        "fonseca": 35,
        "shelton": 8,
        "djokovic": 3,
        "alcaraz": 1,
        "de-minaur": 6,
        "sinner": 2,
        "fritz": 7,
        "musetti": 5,
        "rublev": 17
      }
    },
    {
      "date": "2026-03-16",
      "distances": {
        "adriano": 20.6882,
        "alessandro": 32.8024,
        "federico": 36.9459,
        "viola": 3.7417
      },
      "actuals": {
        "zverev": 4,
        "shelton": 9,
        "fonseca": 39,
        "fritz": 7,
        "medvedev": 10,
        "draper": 26,
        "sinner": 2,
        "de-minaur": 6,
        "auger-aliassime": 8,
        "rublev": 16,
        "musetti": 5,
        "alcaraz": 1,
        "djokovic": 3
      }
    },
    {
      "date": "2026-03-23",
      "distances": {
        "adriano": 20.6882,
        "alessandro": 32.8024,
        "federico": 36.9459,
        "viola": 3.7417
      },
      "actuals": {
        "musetti": 5,
        "shelton": 9,
        "djokovic": 3,
        "alcaraz": 1,
        "rublev": 16,
        "auger-aliassime": 8,
        "fonseca": 39,
        "sinner": 2,
        "de-minaur": 6,
        "zverev": 4,
        "fritz": 7,
        "draper": 26,
        "medvedev": 10
      }
    },
    {
      "date": "2026-03-30",
      "distances": {
        "adriano": 19.6469,
        "alessandro": 33.9116,
        "federico": 37.2827,
        "viola": 3.7417
      },
      "actuals": {
        "zverev": 3,
        "shelton": 9,
        "fonseca": 40,
        "fritz": 8,
        "medvedev": 10,
        "draper": 25,
        "sinner": 2,
        "de-minaur": 6,
        "auger-aliassime": 7,
        "rublev": 16,
        "musetti": 5,
        "alcaraz": 1,
        "djokovic": 4
      }
    },
    {
      "date": "2026-04-06",
      "distances": {
        "adriano": 19.6977,
        "alessandro": 33.8674,
        "federico": 37.3095,
        "viola": 3.4641
      },
      "actuals": {
        "zverev": 3,
        "shelton": 8,
        "fonseca": 40,
        "fritz": 9,
        "medvedev": 10,
        "draper": 25,
        "sinner": 2,
        "de-minaur": 6,
        "auger-aliassime": 7,
        "rublev": 15,
        "musetti": 5,
        "alcaraz": 1,
        "djokovic": 4
      }
    },
    {
      "date": "2026-04-13",
      "distances": {
        "adriano": 22.3383,
        "alessandro": 29.2916,
        "federico": 34.6699,
        "viola": 5.6569
      },
      "actuals": {
        "zverev": 3,
        "shelton": 6,
        "fonseca": 35,
        "fritz": 8,
        "medvedev": 10,
        "draper": 28,
        "sinner": 1,
        "de-minaur": 7,
        "auger-aliassime": 5,
        "rublev": 15,
        "musetti": 9,
        "alcaraz": 2,
        "djokovic": 4
      }
    },
    {
      "date": "2026-04-20",
      "distances": {
        "adriano": 22.4722,
        "alessandro": 25.04,
        "federico": 31.749,
        "viola": 6.4807
      },
      "actuals": {
        "zverev": 3,
        "shelton": 6,
        "fonseca": 31,
        "fritz": 7,
        "medvedev": 10,
        "draper": 28,
        "sinner": 1,
        "de-minaur": 8,
        "auger-aliassime": 5,
        "rublev": 12,
        "musetti": 9,
        "alcaraz": 2,
        "djokovic": 4
      }
    }
  ]
}